user_envs/__init__.py
user_envs/envs/__init__.py
user_envs/envs/new_lunar.py
user_envs/wrappers/__init__.py
user_envs/wrappers/relative_position.py
user_envs-0.0.2.dist-info/METADATA
user_envs-0.0.2.dist-info/WHEEL
user_envs-0.0.2.dist-info/top_level.txt
user_envs-0.0.2.dist-info/RECORD
